
[
    {
      "id": "aatrox",
      "key": "266",
      "name": "Aatrox",
      
      "icon": "https://ddragon.leagueoflegends.com/cdn/10.22.1/img/champion/Aatrox.png"
    },
    {
      "id": "ahri",
      "key": "103",
      "name": "Ahri",
      "title": "the Nine-Tailed Fox",
      "icon": "https://ddragon.leagueoflegends.com/cdn/10.22.1/img/champion/Ahri.png"
    },
    {
      "id": "akali",
      "key": "84",
      "name": "Akali",
      
      "icon": "https://ddragon.leagueoflegends.com/cdn/10.22.1/img/champion/Akali.png"
    },
    {
      "id": "alistar",
      "key": "12",
      "name": "Alistar",
      
      "icon": "https://ddragon.leagueoflegends.com/cdn/10.22.1/img/champion/Alistar.png"
    },
    {
      "id": "amumu",
      "key": "32",
      "name": "Amumu",
      
      "icon": "https://ddragon.leagueoflegends.com/cdn/10.22.1/img/champion/Amumu.png"
    },
    {
      "id": "anivia",
      "key": "34",
      "name": "Anivia",
      
      "icon": "https://ddragon.leagueoflegends.com/cdn/10.22.1/img/champion/Anivia.png"
    },
    {
      "id": "annie",
      "key": "1",
      "name": "Annie",
      
      "icon": "https://ddragon.leagueoflegends.com/cdn/10.22.1/img/champion/Annie.png"
    },
    {
      "id": "aphelios",
      "key": "523",
      "name": "Aphelios",
      
      "icon": "https://ddragon.leagueoflegends.com/cdn/10.22.1/img/champion/Aphelios.png"
    },
    {
      "id": "ashe",
      "key": "22",
      "name": "Ashe",
      "title": "the Frost Archer",
      
      "icon": "https://ddragon.leagueoflegends.com/cdn/10.22.1/img/champion/Ashe.png"
    },
    {
      "id": "aurelionsol",
      "key": "136",
      "name": "Aurelion Sol",
      
      "icon": "https://ddragon.leagueoflegends.com/cdn/10.22.1/img/champion/AurelionSol.png"
    },
    {
      "id": "azir",
      "key": "268",
      "name": "Azir",
      "title": "the Emperor of the Sands",
      "icon": "https://ddragon.leagueoflegends.com/cdn/10.22.1/img/champion/Azir.png"
    },
    {
      "id": "bard",
      "key": "432",
      "name": "Bard",
      
      "icon": "https://ddragon.leagueoflegends.com/cdn/10.22.1/img/champion/Bard.png"
    },
    {
      "id": "blitzcrank",
      "key": "53",
      "name": "Blitzcrank",
      
      "icon": "https://ddragon.leagueoflegends.com/cdn/10.22.1/img/champion/Blitzcrank.png"
    },
    {
      "id": "brand",
      "key": "63",
      "name": "Brand",
      
      "icon": "https://ddragon.leagueoflegends.com/cdn/10.22.1/img/champion/Brand.png"
    },
    {
      "id": "braum",
      "key": "201",
      "name": "Braum",
      
      "icon": "https://ddragon.leagueoflegends.com/cdn/10.22.1/img/champion/Braum.png"
    },
    {
      "id": "caitlyn",
      "key": "51",
      "name": "Caitlyn",
      
      "icon": "https://ddragon.leagueoflegends.com/cdn/10.22.1/img/champion/Caitlyn.png"
    },
    {
      "id": "camille",
      "key": "164",
      "name": "Camille",
      
      "icon": "https://ddragon.leagueoflegends.com/cdn/10.22.1/img/champion/Camille.png"
    },
    {
      "id": "cassiopeia",
      "key": "69",
      "name": "Cassiopeia",
      
      "icon": "https://ddragon.leagueoflegends.com/cdn/10.22.1/img/champion/Cassiopeia.png"
    },
    {
      "id": "chogath",
      "key": "31",
      "name": "Cho'Gath",
      
      "icon": "https://ddragon.leagueoflegends.com/cdn/10.22.1/img/champion/Chogath.png"
    },
    {
      "id": "corki",
      "key": "42",
      "name": "Corki",
      
      "icon": "https://ddragon.leagueoflegends.com/cdn/10.22.1/img/champion/Corki.png"
    },
    {
      "id": "darius",
      "key": "122",
      "name": "Darius",
      
      "icon": "https://ddragon.leagueoflegends.com/cdn/10.22.1/img/champion/Darius.png"
    },
    {
      "id": "diana",
      "key": "131",
      "name": "Diana",
      
      "icon": "https://ddragon.leagueoflegends.com/cdn/10.22.1/img/champion/Diana.png"
    },
    {
      "id": "draven",
      "key": "119",
      "name": "Draven",
      
      "icon": "https://ddragon.leagueoflegends.com/cdn/10.22.1/img/champion/Draven.png"
    },
    {
      "id": "drmundo",
      "key": "36",
      "name": "Dr. Mundo",
      
      "icon": "https://ddragon.leagueoflegends.com/cdn/10.22.1/img/champion/DrMundo.png"
    },
    {
      "id": "ekko",
      "key": "245",
      "name": "Ekko",
      "title": "the Boy Who Shattered Time",
      
      "icon": "https://ddragon.leagueoflegends.com/cdn/10.22.1/img/champion/Ekko.png"
    },
    {
      "id": "elise",
      "key": "60",
      "name": "Elise",
      
      "icon": "https://ddragon.leagueoflegends.com/cdn/10.22.1/img/champion/Elise.png"
    },
    {
      "id": "evelynn",
      "key": "28",
      "name": "Evelynn",
      "title": "Agony's Embrace",
      "icon": "https://ddragon.leagueoflegends.com/cdn/10.22.1/img/champion/Evelynn.png"
    },
    {
      "id": "ezreal",
      "key": "81",
      "name": "Ezreal",
      "title": "the Prodigal Explorer",
      "icon": "https://ddragon.leagueoflegends.com/cdn/10.22.1/img/champion/Ezreal.png"
    },
    {
      "id": "fiddlesticks",
      "key": "9",
      "name": "Fiddlesticks",
      
      "icon": "https://ddragon.leagueoflegends.com/cdn/10.22.1/img/champion/Fiddlesticks.png"
    },
    {
      "id": "fiora",
      "key": "114",
      "name": "Fiora",
      "title": "the Grand Duelist",
      
      "icon": "https://ddragon.leagueoflegends.com/cdn/10.22.1/img/champion/Fiora.png"
    },
    {
      "id": "fizz",
      "key": "105",
      "name": "Fizz",
      "title": "the Tidal Trickster",
      
      "icon": "https://ddragon.leagueoflegends.com/cdn/10.22.1/img/champion/Fizz.png"
    },
    {
      "id": "galio",
      "key": "3",
      "name": "Galio",
      
      "icon": "https://ddragon.leagueoflegends.com/cdn/10.22.1/img/champion/Galio.png"
    },
    {
      "id": "gangplank",
      "key": "41",
      "name": "Gangplank",
      
      "icon": "https://ddragon.leagueoflegends.com/cdn/10.22.1/img/champion/Gangplank.png"
    },
    {
      "id": "garen",
      "key": "86",
      "name": "Garen",
      
      "icon": "https://ddragon.leagueoflegends.com/cdn/10.22.1/img/champion/Garen.png"
    },
    {
      "id": "gnar",
      "key": "150",
      "name": "Gnar",
      
      "icon": "https://ddragon.leagueoflegends.com/cdn/10.22.1/img/champion/Gnar.png"
    },
    {
      "id": "gragas",
      "key": "79",
      "name": "Gragas",
      
      "icon": "https://ddragon.leagueoflegends.com/cdn/10.22.1/img/champion/Gragas.png"
    },
    {
      "id": "graves",
      "key": "104",
      "name": "Graves",
      
      "icon": "https://ddragon.leagueoflegends.com/cdn/10.22.1/img/champion/Graves.png"
    },
    {
      "id": "hecarim",
      "key": "120",
      "name": "Hecarim",
      
      "icon": "https://ddragon.leagueoflegends.com/cdn/10.22.1/img/champion/Hecarim.png"
    },
    {
      "id": "heimerdinger",
      "key": "74",
      "name": "Heimerdinger",
      
      "icon": "https://ddragon.leagueoflegends.com/cdn/10.22.1/img/champion/Heimerdinger.png"
    },
    {
      "id": "illaoi",
      "key": "420",
      "name": "Illaoi",
      
      "icon": "https://ddragon.leagueoflegends.com/cdn/10.22.1/img/champion/Illaoi.png"
    },
    {
      "id": "irelia",
      "key": "39",
      "name": "Irelia",
      "title": "the Blade Dancer",
      
      "icon": "https://ddragon.leagueoflegends.com/cdn/10.22.1/img/champion/Irelia.png"
    },
    {
      "id": "ivern",
      "key": "427",
      "name": "Ivern",
      
      "icon": "https://ddragon.leagueoflegends.com/cdn/10.22.1/img/champion/Ivern.png"
    },
    {
      "id": "janna",
      "key": "40",
      "name": "Janna",
      
      "icon": "https://ddragon.leagueoflegends.com/cdn/10.22.1/img/champion/Janna.png"
    },
    {
      "id": "jarvaniv",
      "key": "59",
      "name": "Jarvan IV",
      
      "icon": "https://ddragon.leagueoflegends.com/cdn/10.22.1/img/champion/JarvanIV.png"
    },
    {
      "id": "jax",
      "key": "24",
      "name": "Jax",
      "title": "Grandmaster at Arms",
      
      "icon": "https://ddragon.leagueoflegends.com/cdn/10.22.1/img/champion/Jax.png"
    },
    {
      "id": "jayce",
      "key": "126",
      "name": "Jayce",
      "title": "the Defender of Tomorrow",
      
      "icon": "https://ddragon.leagueoflegends.com/cdn/10.22.1/img/champion/Jayce.png"
    },
    {
      "id": "jhin",
      "key": "202",
      "name": "Jhin",
      "title": "the Virtuoso",
      "icon": "https://ddragon.leagueoflegends.com/cdn/10.22.1/img/champion/Jhin.png"
    },
    {
      "id": "jinx",
      "key": "222",
      "name": "Jinx",
      
      "icon": "https://ddragon.leagueoflegends.com/cdn/10.22.1/img/champion/Jinx.png"
    },
    {
      "id": "kaisa",
      "key": "145",
      "name": "Kai'Sa",
      
      "icon": "https://ddragon.leagueoflegends.com/cdn/10.22.1/img/champion/Kaisa.png"
    },
    {
      "id": "kalista",
      "key": "429",
      "name": "Kalista",
      
      "icon": "https://ddragon.leagueoflegends.com/cdn/10.22.1/img/champion/Kalista.png"
    },
    {
      "id": "karma",
      "key": "43",
      "name": "Karma",
      
      "icon": "https://ddragon.leagueoflegends.com/cdn/10.22.1/img/champion/Karma.png"
    },
    {
      "id": "karthus",
      "key": "30",
      "name": "Karthus",
      
      "icon": "https://ddragon.leagueoflegends.com/cdn/10.22.1/img/champion/Karthus.png"
    },
    {
      "id": "kassadin",
      "key": "38",
      "name": "Kassadin",
      "title": "the Void Walker",
      "icon": "https://ddragon.leagueoflegends.com/cdn/10.22.1/img/champion/Kassadin.png"
    },
    {
      "id": "katarina",
      "key": "55",
      "name": "Katarina",
      "title": "the Sinister Blade",
      "icon": "https://ddragon.leagueoflegends.com/cdn/10.22.1/img/champion/Katarina.png"
    },
    {
      "id": "kayle",
      "key": "10",
      "name": "Kayle",
      "title": "the Righteous",

      "icon": "https://ddragon.leagueoflegends.com/cdn/10.22.1/img/champion/Kayle.png"
    },
    {
      "id": "kayn",
      "key": "141",
      "name": "Kayn",
      "title": "the Shadow Reaper",
      
      "icon": "https://ddragon.leagueoflegends.com/cdn/10.22.1/img/champion/Kayn.png"
    },
    {
      "id": "kennen",
      "key": "85",
      "name": "Kennen",
      "title": "the Heart of the Tempest",
      "icon": "https://ddragon.leagueoflegends.com/cdn/10.22.1/img/champion/Kennen.png"
    },
    {
      "id": "khazix",
      "key": "121",
      "name": "Kha'Zix",
      
      "icon": "https://ddragon.leagueoflegends.com/cdn/10.22.1/img/champion/Khazix.png"
    },
    {
      "id": "kindred",
      "key": "203",
      "name": "Kindred",
      
      "icon": "https://ddragon.leagueoflegends.com/cdn/10.22.1/img/champion/Kindred.png"
    },
    {
      "id": "kled",
      "key": "240",
      "name": "Kled",
      
      "icon": "https://ddragon.leagueoflegends.com/cdn/10.22.1/img/champion/Kled.png"
    },
    {
      "id": "kogmaw",
      "key": "96",
      "name": "Kog'Maw",
      "title": "the Mouth of the Abyss",
      "icon": "https://ddragon.leagueoflegends.com/cdn/10.22.1/img/champion/KogMaw.png"
    },
    {
      "id": "leblanc",
      "key": "7",
      "name": "LeBlanc",
      "title": "the Deceiver",
      "icon": "https://ddragon.leagueoflegends.com/cdn/10.22.1/img/champion/Leblanc.png"
    },
    {
      "id": "leesin",
      "key": "64",
      "name": "Lee Sin",
      "title": "the Blind Monk",
      
      "icon": "https://ddragon.leagueoflegends.com/cdn/10.22.1/img/champion/LeeSin.png"
    },
    {
      "id": "leona",
      "key": "89",
      "name": "Leona",
      
      "icon": "https://ddragon.leagueoflegends.com/cdn/10.22.1/img/champion/Leona.png"
    },
    {
      "id": "lillia",
      "key": "876",
      "name": "Lillia",
      
      "icon": "https://ddragon.leagueoflegends.com/cdn/10.22.1/img/champion/Lillia.png"
    },
    {
      "id": "lissandra",
      "key": "127",
      "name": "Lissandra",
      
      "icon": "https://ddragon.leagueoflegends.com/cdn/10.22.1/img/champion/Lissandra.png"
    },
    {
      "id": "lucian",
      "key": "236",
      "name": "Lucian",
      
      "icon": "https://ddragon.leagueoflegends.com/cdn/10.22.1/img/champion/Lucian.png"
    },
    {
      "id": "lulu",
      "key": "117",
      "name": "Lulu",
      
      "icon": "https://ddragon.leagueoflegends.com/cdn/10.22.1/img/champion/Lulu.png"
    },
    {
      "id": "lux",
      "key": "99",
      "name": "Lux",
      
      "icon": "https://ddragon.leagueoflegends.com/cdn/10.22.1/img/champion/Lux.png"
    },
    {
      "id": "malphite",
      "key": "54",
      "name": "Malphite",
      
      "icon": "https://ddragon.leagueoflegends.com/cdn/10.22.1/img/champion/Malphite.png"
    },
    {
      "id": "malzahar",
      "key": "90",
      "name": "Malzahar",
      "title": "the Prophet of the Void",
      "icon": "https://ddragon.leagueoflegends.com/cdn/10.22.1/img/champion/Malzahar.png"
    },
    {
      "id": "maokai",
      "key": "57",
      "name": "Maokai",
      
      "icon": "https://ddragon.leagueoflegends.com/cdn/10.22.1/img/champion/Maokai.png"
    },
    {
      "id": "masteryi",
      "key": "11",
      "name": "Master Yi",
      "title": "the Wuju Bladesman",
      
      "icon": "https://ddragon.leagueoflegends.com/cdn/10.22.1/img/champion/MasterYi.png"
    },
    {
      "id": "missfortune",
      "key": "21",
      "name": "Miss Fortune",
      
      "icon": "https://ddragon.leagueoflegends.com/cdn/10.22.1/img/champion/MissFortune.png"
    },
    {
      "id": "monkeyking",
      "key": "62",
      "name": "Wukong",
      
      "icon": "https://ddragon.leagueoflegends.com/cdn/10.22.1/img/champion/MonkeyKing.png"
    },
    {
      "id": "mordekaiser",
      "key": "82",
      "name": "Mordekaiser",
      
      "icon": "https://ddragon.leagueoflegends.com/cdn/10.22.1/img/champion/Mordekaiser.png"
    },
    {
      "id": "morgana",
      "key": "25",
      "name": "Morgana",
      
      "icon": "https://ddragon.leagueoflegends.com/cdn/10.22.1/img/champion/Morgana.png"
    },
    {
      "id": "nami",
      "key": "267",
      "name": "Nami",
      
      "icon": "https://ddragon.leagueoflegends.com/cdn/10.22.1/img/champion/Nami.png"
    },
    {
      "id": "nasus",
      "key": "75",
      "name": "Nasus",
      
      "icon": "https://ddragon.leagueoflegends.com/cdn/10.22.1/img/champion/Nasus.png"
    },
    {
      "id": "nautilus",
      "key": "111",
      "name": "Nautilus",
      
      "icon": "https://ddragon.leagueoflegends.com/cdn/10.22.1/img/champion/Nautilus.png"
    },
    {
      "id": "neeko",
      "key": "518",
      "name": "Neeko",
      
      "icon": "https://ddragon.leagueoflegends.com/cdn/10.22.1/img/champion/Neeko.png"
    },
    {
      "id": "nidalee",
      "key": "76",
      "name": "Nidalee",
      "title": "the Bestial Huntress",
      "icon": "https://ddragon.leagueoflegends.com/cdn/10.22.1/img/champion/Nidalee.png"
    },
    {
      "id": "nocturne",
      "key": "56",
      "name": "Nocturne",
      "title": "the Eternal Nightmare",
      
      "icon": "https://ddragon.leagueoflegends.com/cdn/10.22.1/img/champion/Nocturne.png"
    },
    {
      "id": "nunu",
      "key": "20",
      "name": "Nunu & Willump",
      
      "icon": "https://ddragon.leagueoflegends.com/cdn/10.22.1/img/champion/Nunu.png"
    },
    {
      "id": "olaf",
      "key": "2",
      "name": "Olaf",
      
      "icon": "https://ddragon.leagueoflegends.com/cdn/10.22.1/img/champion/Olaf.png"
    },
    {
      "id": "orianna",
      "key": "61",
      "name": "Orianna",
      
      "icon": "https://ddragon.leagueoflegends.com/cdn/10.22.1/img/champion/Orianna.png"
    },
    {
      "id": "ornn",
      "key": "516",
      "name": "Ornn",
      
      "icon": "https://ddragon.leagueoflegends.com/cdn/10.22.1/img/champion/Ornn.png"
    },
    {
      "id": "pantheon",
      "key": "80",
      "name": "Pantheon",
      "title": "the Unbreakable Spear",
      
      "icon": "https://ddragon.leagueoflegends.com/cdn/10.22.1/img/champion/Pantheon.png"
    },
    {
      "id": "poppy",
      "key": "78",
      "name": "Poppy",
      
      "icon": "https://ddragon.leagueoflegends.com/cdn/10.22.1/img/champion/Poppy.png"
    },
    {
      "id": "pyke",
      "key": "555",
      "name": "Pyke",
      "title": "the Bloodharbor Ripper",
      
      "icon": "https://ddragon.leagueoflegends.com/cdn/10.22.1/img/champion/Pyke.png"
    },
    {
      "id": "qiyana",
      "key": "246",
      "name": "Qiyana",
      "title": "Empress of the Elements",
      
      "icon": "https://ddragon.leagueoflegends.com/cdn/10.22.1/img/champion/Qiyana.png"
    },
    {
      "id": "quinn",
      "key": "133",
      "name": "Quinn",
      "title": "Demacia's Wings",
      
      "icon": "https://ddragon.leagueoflegends.com/cdn/10.22.1/img/champion/Quinn.png"
    },
    {
      "id": "rakan",
      "key": "497",
      "name": "Rakan",
      
      "icon": "https://ddragon.leagueoflegends.com/cdn/10.22.1/img/champion/Rakan.png"
    },
    {
      "id": "rammus",
      "key": "33",
      "name": "Rammus",
      
      "icon": "https://ddragon.leagueoflegends.com/cdn/10.22.1/img/champion/Rammus.png"
    },
    {
      "id": "reksai",
      "key": "421",
      "name": "Rek'Sai",
      
      "icon": "https://ddragon.leagueoflegends.com/cdn/10.22.1/img/champion/RekSai.png"
    },
    {
      "id": "renekton",
      "key": "58",
      "name": "Renekton",
      
      "icon": "https://ddragon.leagueoflegends.com/cdn/10.22.1/img/champion/Renekton.png"
    },
    {
      "id": "rengar",
      "key": "107",
      "name": "Rengar",
      "title": "the Pridestalker",
      
      "icon": "https://ddragon.leagueoflegends.com/cdn/10.22.1/img/champion/Rengar.png"
    },
    {
      "id": "riven",
      "key": "92",
      "name": "Riven",
      "title": "the Exile",
      
      "icon": "https://ddragon.leagueoflegends.com/cdn/10.22.1/img/champion/Riven.png"
    },
    {
      "id": "rumble",
      "key": "68",
      "name": "Rumble",
      
      "icon": "https://ddragon.leagueoflegends.com/cdn/10.22.1/img/champion/Rumble.png"
    },
    {
      "id": "ryze",
      "key": "13",
      "name": "Ryze",
      
      "icon": "https://ddragon.leagueoflegends.com/cdn/10.22.1/img/champion/Ryze.png"
    },
    {
      "id": "samira",
      "key": "360",
      "name": "Samira",
      
      "icon": "https://ddragon.leagueoflegends.com/cdn/10.22.1/img/champion/Samira.png"
    },
    {
      "id": "sejuani",
      "key": "113",
      "name": "Sejuani",
      
      "icon": "https://ddragon.leagueoflegends.com/cdn/10.22.1/img/champion/Sejuani.png"
    },
    {
      "id": "senna",
      "key": "235",
      "name": "Senna",
      "title": "the Redeemer",
      
      "icon": "https://ddragon.leagueoflegends.com/cdn/10.22.1/img/champion/Senna.png"
    },
    {
      "id": "seraphine",
      "key": "147",
      "name": "Seraphine",
      
      "icon": "https://ddragon.leagueoflegends.com/cdn/10.22.1/img/champion/Seraphine.png"
    },
    {
      "id": "sett",
      "key": "875",
      "name": "Sett",
      
      "icon": "https://ddragon.leagueoflegends.com/cdn/10.22.1/img/champion/Sett.png"
    },
    {
      "id": "shaco",
      "key": "35",
      "name": "Shaco",
      
      "icon": "https://ddragon.leagueoflegends.com/cdn/10.22.1/img/champion/Shaco.png"
    },
    {
      "id": "shen",
      "key": "98",
      "name": "Shen",
      
      "icon": "https://ddragon.leagueoflegends.com/cdn/10.22.1/img/champion/Shen.png"
    },
    {
      "id": "shyvana",
      "key": "102",
      "name": "Shyvana",
      
      "icon": "https://ddragon.leagueoflegends.com/cdn/10.22.1/img/champion/Shyvana.png"
    },
    {
      "id": "singed",
      "key": "27",
      "name": "Singed",
      
      "icon": "https://ddragon.leagueoflegends.com/cdn/10.22.1/img/champion/Singed.png"
    },
    {
      "id": "sion",
      "key": "14",
      "name": "Sion",
      
      "icon": "https://ddragon.leagueoflegends.com/cdn/10.22.1/img/champion/Sion.png"
    },
    {
      "id": "sivir",
      "key": "15",
      "name": "Sivir",
      
      "icon": "https://ddragon.leagueoflegends.com/cdn/10.22.1/img/champion/Sivir.png"
    },
    {
      "id": "skarner",
      "key": "72",
      "name": "Skarner",
      
      "icon": "https://ddragon.leagueoflegends.com/cdn/10.22.1/img/champion/Skarner.png"
    },
    {
      "id": "sona",
      "key": "37",
      "name": "Sona",
      
      "icon": "https://ddragon.leagueoflegends.com/cdn/10.22.1/img/champion/Sona.png"
    },
    {
      "id": "soraka",
      "key": "16",
      "name": "Soraka",
      
      "icon": "https://ddragon.leagueoflegends.com/cdn/10.22.1/img/champion/Soraka.png"
    },
    {
      "id": "swain",
      "key": "50",
      "name": "Swain",
      
      "icon": "https://ddragon.leagueoflegends.com/cdn/10.22.1/img/champion/Swain.png"
    },
    {
      "id": "sylas",
      "key": "517",
      "name": "Sylas",
      "title": "the Unshackled",
      "icon": "https://ddragon.leagueoflegends.com/cdn/10.22.1/img/champion/Sylas.png"
    },
    {
      "id": "syndra",
      "key": "134",
      "name": "Syndra",
      
      "icon": "https://ddragon.leagueoflegends.com/cdn/10.22.1/img/champion/Syndra.png"
    },
    {
      "id": "tahmkench",
      "key": "223",
      "name": "Tahm Kench",
      
      "icon": "https://ddragon.leagueoflegends.com/cdn/10.22.1/img/champion/TahmKench.png"
    },
    {
      "id": "taliyah",
      "key": "163",
      "name": "Taliyah",
      
      "icon": "https://ddragon.leagueoflegends.com/cdn/10.22.1/img/champion/Taliyah.png"
    },
    {
      "id": "talon",
      "key": "91",
      "name": "Talon",
      
      "icon": "https://ddragon.leagueoflegends.com/cdn/10.22.1/img/champion/Talon.png"
    },
    {
      "id": "taric",
      "key": "44",
      "name": "Taric",
      "title": "the Shield of Valoran",

      "icon": "https://ddragon.leagueoflegends.com/cdn/10.22.1/img/champion/Taric.png"
    },
    {
      "id": "teemo",
      "key": "17",
      "name": "Teemo",
      "title": "the Swift Scout",
      
      "icon": "https://ddragon.leagueoflegends.com/cdn/10.22.1/img/champion/Teemo.png"
    },
    {
      "id": "thresh",
      "key": "412",
      "name": "Thresh",
      "title": "the Chain Warden",

      "icon": "https://ddragon.leagueoflegends.com/cdn/10.22.1/img/champion/Thresh.png"
    },
    {
      "id": "tristana",
      "key": "18",
      "name": "Tristana",
      "title": "the Yordle Gunner",
      
      "icon": "https://ddragon.leagueoflegends.com/cdn/10.22.1/img/champion/Tristana.png"
    },
    {
      "id": "trundle",
      "key": "48",
      "name": "Trundle",
      
      "icon": "https://ddragon.leagueoflegends.com/cdn/10.22.1/img/champion/Trundle.png"
    },
    {
      "id": "tryndamere",
      "key": "23",
      "name": "Tryndamere",
      "title": "the Barbarian King",
      
      "icon": "https://ddragon.leagueoflegends.com/cdn/10.22.1/img/champion/Tryndamere.png"
    },
    {
      "id": "twistedfate",
      "key": "4",
      "name": "Twisted Fate",
      
      "icon": "https://ddragon.leagueoflegends.com/cdn/10.22.1/img/champion/TwistedFate.png"
    },
    {
      "id": "twitch",
      "key": "29",
      "name": "Twitch",
      "title": "the Plague Rat",
      
      "icon": "https://ddragon.leagueoflegends.com/cdn/10.22.1/img/champion/Twitch.png"
    },
    {
      "id": "udyr",
      "key": "77",
      "name": "Udyr",
      
      "icon": "https://ddragon.leagueoflegends.com/cdn/10.22.1/img/champion/Udyr.png"
    },
    {
      "id": "urgot",
      "key": "6",
      "name": "Urgot",
      
      "icon": "https://ddragon.leagueoflegends.com/cdn/10.22.1/img/champion/Urgot.png"
    },
    {
      "id": "varus",
      "key": "110",
      "name": "Varus",
      "title": "the Arrow of Retribution",
      "icon": "https://ddragon.leagueoflegends.com/cdn/10.22.1/img/champion/Varus.png"
    },
    {
      "id": "vayne",
      "key": "67",
      "name": "Vayne",
      "title": "the Night Hunter",
      
      "icon": "https://ddragon.leagueoflegends.com/cdn/10.22.1/img/champion/Vayne.png"
    },
    {
      "id": "veigar",
      "key": "45",
      "name": "Veigar",
      
      "icon": "https://ddragon.leagueoflegends.com/cdn/10.22.1/img/champion/Veigar.png"
    },
    {
      "id": "velkoz",
      "key": "161",
      "name": "Vel'Koz",
      
      "icon": "https://ddragon.leagueoflegends.com/cdn/10.22.1/img/champion/Velkoz.png"
    },
    {
      "id": "vi",
      "key": "254",
      "name": "Vi",
      "title": "the Piltover Enforcer",
      
      "icon": "https://ddragon.leagueoflegends.com/cdn/10.22.1/img/champion/Vi.png"
    },
    {
      "id": "viktor",
      "key": "112",
      "name": "Viktor",
      
      "icon": "https://ddragon.leagueoflegends.com/cdn/10.22.1/img/champion/Viktor.png"
    },
    {
      "id": "vladimir",
      "key": "8",
      "name": "Vladimir",
      
      "icon": "https://ddragon.leagueoflegends.com/cdn/10.22.1/img/champion/Vladimir.png"
    },
    {
      "id": "volibear",
      "key": "106",
      "name": "Volibear",
      
      "icon": "https://ddragon.leagueoflegends.com/cdn/10.22.1/img/champion/Volibear.png"
    },
    {
      "id": "warwick",
      "key": "19",
      "name": "Warwick",
      
      "icon": "https://ddragon.leagueoflegends.com/cdn/10.22.1/img/champion/Warwick.png"
    },
    {
      "id": "xayah",
      "key": "498",
      "name": "Xayah",
      
      "icon": "https://ddragon.leagueoflegends.com/cdn/10.22.1/img/champion/Xayah.png"
    },
    {
      "id": "xerath",
      "key": "101",
      "name": "Xerath",
      
      "icon": "https://ddragon.leagueoflegends.com/cdn/10.22.1/img/champion/Xerath.png"
    },
    {
      "id": "xinzhao",
      "key": "5",
      "name": "Xin Zhao",
      "title": "the Seneschal of Demacia",
      
      "icon": "https://ddragon.leagueoflegends.com/cdn/10.22.1/img/champion/XinZhao.png"
    },
    {
      "id": "yasuo",
      "key": "157",
      "name": "Yasuo",
      "title": "the Unforgiven",
      
      "icon": "https://ddragon.leagueoflegends.com/cdn/10.22.1/img/champion/Yasuo.png"
    },
    {
      "id": "yone",
      "key": "777",
      "name": "Yone",
      "title": "the Unforgotten",
      
      "icon": "https://ddragon.leagueoflegends.com/cdn/10.22.1/img/champion/Yone.png"
    },
    {
      "id": "yorick",
      "key": "83",
      "name": "Yorick",
      
      "icon": "https://ddragon.leagueoflegends.com/cdn/10.22.1/img/champion/Yorick.png"
    },
    {
      "id": "yuumi",
      "key": "350",
      "name": "Yuumi",
      
      "icon": "https://ddragon.leagueoflegends.com/cdn/10.22.1/img/champion/Yuumi.png"
    },
    {
      "id": "zac",
      "key": "154",
      "name": "Zac",
      
      "icon": "https://ddragon.leagueoflegends.com/cdn/10.22.1/img/champion/Zac.png"
    },
    {
      "id": "zed",
      "key": "238",
      "name": "Zed",
      
      "icon": "https://ddragon.leagueoflegends.com/cdn/10.22.1/img/champion/Zed.png"
    },
    {
      "id": "ziggs",
      "key": "115",
      "name": "Ziggs",
      
      "icon": "https://ddragon.leagueoflegends.com/cdn/10.22.1/img/champion/Ziggs.png"
    },
    {
      "id": "zilean",
      "key": "26",
      "name": "Zilean",
      
      "icon": "https://ddragon.leagueoflegends.com/cdn/10.22.1/img/champion/Zilean.png"
    },
    {
      "id": "zoe",
      "key": "142",
      "name": "Zoe",
      
      "icon": "https://ddragon.leagueoflegends.com/cdn/10.22.1/img/champion/Zoe.png"
    },
    {
      "id": "zyra",
      "key": "143",
      "name": "Zyra",
      
      "icon": "https://ddragon.leagueoflegends.com/cdn/10.22.1/img/champion/Zyra.png"
    }
  ]
  